virtualcandy/__init__.py
virtualcandy/lib/tmpl/pkg_init.tmpl.sh
virtualcandy/lib/tmpl/pkg_makefile.tmpl.sh
virtualcandy/lib/tmpl/pkg_setup.tmpl.sh
virtualcandy/lib/vc_common_code.sh
virtualcandy/lib/vc_config.sh
virtualcandy/lib/virtualcandy.sh
virtualcandy/lib/virtualcandy.zsh
virtualcandy/vcshellinstaller
virtualcandy-3.0.1.dist-info/LICENSE.txt
virtualcandy-3.0.1.dist-info/WHEEL
virtualcandy-3.0.1.dist-info/METADATA
virtualcandy-3.0.1.dist-info/RECORD
