Metadata-Version: 2.1
Name: virtualcandy
Version: 3.0.1
Summary: Virtualcandy provides Virtualenv_ integration with your Bash or Zsh shell
License: BSD-3-Clause
Author: Jeff Buttars
Author-email: jeffbuttars@gmail.com
Requires-Python: >=3.6,<4.0
Classifier: License :: OSI Approved :: BSD License
Classifier: Programming Language :: Python :: 3
Classifier: Programming Language :: Python :: 3.6
Classifier: Programming Language :: Python :: 3.7
Classifier: Programming Language :: Python :: 3.8
Requires-Dist: flake8 (>=3.8.3,<4.0.0)
Requires-Dist: pip (>=20.1.1,<21.0.0)
